[
  {
    "url": "https://spearfish.blackhills.bywatersolutions.com/cgi-bin/koha/opac-detail.pl?biblionumber=521809",
    "title": "Chickens and other dinosaurs",
    "image_url": "https://images-na.ssl-images-amazon.com/images/P/1804537802.01.LZZZZZZZ.jpg",
    "record_type": "library_book",
    "source_label": "Grace Balloch Memorial Library"
  },
  {
    "url": "https://spearfish.blackhills.bywatersolutions.com/cgi-bin/koha/opac-detail.pl?biblionumber=520434",
    "title": "Zine Making and Bookbinding: A Beginner's Guide in 25 Projects",
    "image_url": "https://images-na.ssl-images-amazon.com/images/P/1797238752.01.LZZZZZZZ.jpg",
    "record_type": "library_book",
    "source_label": "Grace Balloch Memorial Library"
  },
  {
    "url": "https://spearfish.blackhills.bywatersolutions.com/cgi-bin/koha/opac-detail.pl?biblionumber=516683",
    "title": "The bookstore diaries",
    "image_url": "https://images-na.ssl-images-amazon.com/images/P/133562970X.01.LZZZZZZZ.jpg",
    "record_type": "library_book",
    "source_label": "Grace Balloch Memorial Library"
  },
  {
    "url": "https://spearfish.blackhills.bywatersolutions.com/cgi-bin/koha/opac-detail.pl?biblionumber=521476",
    "title": "Drawing Is Important",
    "image_url": "https://images-na.ssl-images-amazon.com/images/P/0760399468.01.LZZZZZZZ.jpg",
    "record_type": "library_book",
    "source_label": "Grace Balloch Memorial Library"
  },
  {
    "url": "https://spearfish.blackhills.bywatersolutions.com/cgi-bin/koha/opac-detail.pl?biblionumber=521131",
    "title": "Two old broads",
    "image_url": "https://images-na.ssl-images-amazon.com/images/P/0785241647.01.LZZZZZZZ.jpg",
    "record_type": "library_book",
    "source_label": "Grace Balloch Memorial Library"
  },
  {
    "url": "https://spearfish.blackhills.bywatersolutions.com/cgi-bin/koha/opac-detail.pl?biblionumber=520190",
    "title": "An anthology of stargazing",
    "image_url": "",
    "record_type": "library_book",
    "source_label": "Grace Balloch Memorial Library"
  },
  {
    "url": "https://spearfish.blackhills.bywatersolutions.com/cgi-bin/koha/opac-detail.pl?biblionumber=522546",
    "title": "Fighter and reconnaissance aircraft",
    "image_url": "https://images-na.ssl-images-amazon.com/images/P/0785829946.01.LZZZZZZZ.jpg",
    "record_type": "library_book",
    "source_label": "Grace Balloch Memorial Library"
  },
  {
    "url": "https://spearfish.blackhills.bywatersolutions.com/cgi-bin/koha/opac-detail.pl?biblionumber=521639",
    "title": "Welcome to the Funny Farm",
    "image_url": "https://images-na.ssl-images-amazon.com/images/P/0739418726.01.LZZZZZZZ.jpg",
    "record_type": "library_book",
    "source_label": "Grace Balloch Memorial Library"
  },
  {
    "url": "https://spearfish.blackhills.bywatersolutions.com/cgi-bin/koha/opac-detail.pl?biblionumber=169916",
    "title": "The eagle has landed",
    "image_url": "https://images-na.ssl-images-amazon.com/images/P/0030137462.01.LZZZZZZZ.jpg",
    "record_type": "library_book",
    "source_label": "Grace Balloch Memorial Library"
  },
  {
    "url": "https://spearfish.blackhills.bywatersolutions.com/cgi-bin/koha/opac-detail.pl?biblionumber=65869",
    "title": "Watch the skies",
    "image_url": "https://images-na.ssl-images-amazon.com/images/P/0316036188.01.LZZZZZZZ.jpg",
    "record_type": "library_book",
    "source_label": "Grace Balloch Memorial Library"
  },
  {
    "url": "https://spearfish.blackhills.bywatersolutions.com/cgi-bin/koha/opac-detail.pl?biblionumber=253073",
    "title": "Dreams",
    "image_url": "https://images-na.ssl-images-amazon.com/images/P/0760709300.01.LZZZZZZZ.jpg",
    "record_type": "library_book",
    "source_label": "Grace Balloch Memorial Library"
  },
  {
    "url": "https://spearfish.blackhills.bywatersolutions.com/cgi-bin/koha/opac-detail.pl?biblionumber=167864",
    "title": "Simple machines",
    "image_url": "https://images-na.ssl-images-amazon.com/images/P/0823433099.01.LZZZZZZZ.jpg",
    "record_type": "library_book",
    "source_label": "Grace Balloch Memorial Library"
  },
  {
    "url": "https://spearfish.blackhills.bywatersolutions.com/cgi-bin/koha/opac-detail.pl?biblionumber=516458",
    "title": "Hope rises",
    "image_url": "https://images-na.ssl-images-amazon.com/images/P/1538758024.01.LZZZZZZZ.jpg",
    "record_type": "library_book",
    "source_label": "Grace Balloch Memorial Library"
  },
  {
    "url": "https://spearfish.blackhills.bywatersolutions.com/cgi-bin/koha/opac-detail.pl?biblionumber=257750",
    "title": "Kiss her goodbye",
    "image_url": "https://images-na.ssl-images-amazon.com/images/P/0312358393.01.LZZZZZZZ.jpg",
    "record_type": "library_book",
    "source_label": "Grace Balloch Memorial Library"
  },
  {
    "url": "https://spearfish.blackhills.bywatersolutions.com/cgi-bin/koha/opac-detail.pl?biblionumber=511927",
    "title": "Solitary Animals",
    "image_url": "https://images-na.ssl-images-amazon.com/images/P/0593661087.01.LZZZZZZZ.jpg",
    "record_type": "library_book",
    "source_label": "Grace Balloch Memorial Library"
  },
  {
    "url": "https://spearfish.blackhills.bywatersolutions.com/cgi-bin/koha/opac-detail.pl?biblionumber=99785",
    "title": "Confessions of a sociopath",
    "image_url": "https://images-na.ssl-images-amazon.com/images/P/0307956644.01.LZZZZZZZ.jpg",
    "record_type": "library_book",
    "source_label": "Grace Balloch Memorial Library"
  },
  {
    "url": "https://spearfish.blackhills.bywatersolutions.com/cgi-bin/koha/opac-detail.pl?biblionumber=510219",
    "title": "The Marigold Cottages murder collective",
    "image_url": "https://images-na.ssl-images-amazon.com/images/P/1250356547.01.LZZZZZZZ.jpg",
    "record_type": "library_book",
    "source_label": "Grace Balloch Memorial Library"
  },
  {
    "url": "https://spearfish.blackhills.bywatersolutions.com/cgi-bin/koha/opac-detail.pl?biblionumber=520476",
    "title": "I'm so happy you're here",
    "image_url": "",
    "record_type": "library_book",
    "source_label": "Grace Balloch Memorial Library"
  },
  {
    "url": "https://spearfish.blackhills.bywatersolutions.com/cgi-bin/koha/opac-detail.pl?biblionumber=522213",
    "title": "A lethal truth",
    "image_url": "https://images-na.ssl-images-amazon.com/images/P/1335980245.01.LZZZZZZZ.jpg",
    "record_type": "library_book",
    "source_label": "Grace Balloch Memorial Library"
  },
  {
    "url": "https://spearfish.blackhills.bywatersolutions.com/cgi-bin/koha/opac-detail.pl?biblionumber=520654",
    "title": "One & only",
    "image_url": "",
    "record_type": "library_book",
    "source_label": "Grace Balloch Memorial Library"
  },
  {
    "url": "https://spearfish.blackhills.bywatersolutions.com/cgi-bin/koha/opac-detail.pl?biblionumber=493524",
    "title": "Rosie Frost & the Falcon Queen",
    "image_url": "https://images-na.ssl-images-amazon.com/images/P/0593623347.01.LZZZZZZZ.jpg",
    "record_type": "library_book",
    "source_label": "Grace Balloch Memorial Library"
  },
  {
    "url": "https://spearfish.blackhills.bywatersolutions.com/cgi-bin/koha/opac-detail.pl?biblionumber=88911",
    "title": "Caterpillar to butterfly",
    "image_url": "https://images-na.ssl-images-amazon.com/images/P/142630921X.01.LZZZZZZZ.jpg",
    "record_type": "library_book",
    "source_label": "Grace Balloch Memorial Library"
  },
  {
    "url": "https://spearfish.blackhills.bywatersolutions.com/cgi-bin/koha/opac-detail.pl?biblionumber=520733",
    "title": "Over and under the wetland",
    "image_url": "https://images-na.ssl-images-amazon.com/images/P/1797210874.01.LZZZZZZZ.jpg",
    "record_type": "library_book",
    "source_label": "Grace Balloch Memorial Library"
  },
  {
    "url": "https://spearfish.blackhills.bywatersolutions.com/cgi-bin/koha/opac-detail.pl?biblionumber=517781",
    "title": "Cold War on five continents",
    "image_url": "",
    "record_type": "library_book",
    "source_label": "Grace Balloch Memorial Library"
  },
  {
    "url": "https://spearfish.blackhills.bywatersolutions.com/cgi-bin/koha/opac-detail.pl?biblionumber=518598",
    "title": "The Martha Way: Essential Principles for Mastering Home and Living",
    "image_url": "https://images-na.ssl-images-amazon.com/images/P/0063323303.01.LZZZZZZZ.jpg",
    "record_type": "library_book",
    "source_label": "Grace Balloch Memorial Library"
  },
  {
    "url": "https://spearfish.blackhills.bywatersolutions.com/cgi-bin/koha/opac-detail.pl?biblionumber=522610",
    "title": "5-ingredient Mediterranean cookbook",
    "image_url": "https://images-na.ssl-images-amazon.com/images/P/1577155742.01.LZZZZZZZ.jpg",
    "record_type": "library_book",
    "source_label": "Grace Balloch Memorial Library"
  },
  {
    "url": "https://spearfish.blackhills.bywatersolutions.com/cgi-bin/koha/opac-detail.pl?biblionumber=522607",
    "title": "An Amish second chance",
    "image_url": "https://images-na.ssl-images-amazon.com/images/P/1420534394.01.LZZZZZZZ.jpg",
    "record_type": "library_book",
    "source_label": "Grace Balloch Memorial Library"
  },
  {
    "url": "https://spearfish.blackhills.bywatersolutions.com/cgi-bin/koha/opac-detail.pl?biblionumber=522606",
    "title": "Thunder of the mountain man",
    "image_url": "https://images-na.ssl-images-amazon.com/images/P/1420535137.01.LZZZZZZZ.jpg",
    "record_type": "library_book",
    "source_label": "Grace Balloch Memorial Library"
  },
  {
    "url": "https://spearfish.blackhills.bywatersolutions.com/cgi-bin/koha/opac-detail.pl?biblionumber=516546",
    "title": "The Paris match",
    "image_url": "https://images-na.ssl-images-amazon.com/images/P/0593819373.01.LZZZZZZZ.jpg",
    "record_type": "library_book",
    "source_label": "Grace Balloch Memorial Library"
  },
  {
    "url": "https://spearfish.blackhills.bywatersolutions.com/cgi-bin/koha/opac-detail.pl?biblionumber=522608",
    "title": "Second chances on Huckleberry Hill",
    "image_url": "https://images-na.ssl-images-amazon.com/images/P/1420535013.01.LZZZZZZZ.jpg",
    "record_type": "library_book",
    "source_label": "Grace Balloch Memorial Library"
  },
  {
    "url": "https://spearfish.blackhills.bywatersolutions.com/cgi-bin/koha/opac-detail.pl?biblionumber=507796",
    "title": "The Pigeon won't count to 10!",
    "image_url": "https://images-na.ssl-images-amazon.com/images/P/1454964405.01.LZZZZZZZ.jpg",
    "record_type": "library_book",
    "source_label": "Grace Balloch Memorial Library"
  },
  {
    "url": "https://spearfish.blackhills.bywatersolutions.com/cgi-bin/koha/opac-detail.pl?biblionumber=522609",
    "title": "The healing",
    "image_url": "https://images-na.ssl-images-amazon.com/images/P/142053498X.01.LZZZZZZZ.jpg",
    "record_type": "library_book",
    "source_label": "Grace Balloch Memorial Library"
  },
  {
    "url": "https://spearfish.blackhills.bywatersolutions.com/cgi-bin/koha/opac-detail.pl?biblionumber=522605",
    "title": "The rancher",
    "image_url": "https://images-na.ssl-images-amazon.com/images/P/1420527886.01.LZZZZZZZ.jpg",
    "record_type": "library_book",
    "source_label": "Grace Balloch Memorial Library"
  },
  {
    "url": "https://spearfish.blackhills.bywatersolutions.com/cgi-bin/koha/opac-detail.pl?biblionumber=119857",
    "title": "The Maltese falcon",
    "image_url": "https://spearfish.blackhills.bywatersolutions.com/cgi-bin/koha/opac-image.pl?biblionumber=119857",
    "record_type": "library_book",
    "source_label": "Grace Balloch Memorial Library"
  },
  {
    "url": "https://spearfish.blackhills.bywatersolutions.com/cgi-bin/koha/opac-detail.pl?biblionumber=521655",
    "title": "Prince Caspian",
    "image_url": "https://images-na.ssl-images-amazon.com/images/P/0063435152.01.LZZZZZZZ.jpg",
    "record_type": "library_book",
    "source_label": "Grace Balloch Memorial Library"
  },
  {
    "url": "https://spearfish.blackhills.bywatersolutions.com/cgi-bin/koha/opac-detail.pl?biblionumber=515552",
    "title": "Return of the Maltese Falcon",
    "image_url": "https://images-na.ssl-images-amazon.com/images/P/1835414877.01.LZZZZZZZ.jpg",
    "record_type": "library_book",
    "source_label": "Grace Balloch Memorial Library"
  },
  {
    "url": "https://spearfish.blackhills.bywatersolutions.com/cgi-bin/koha/opac-detail.pl?biblionumber=517290",
    "title": "Wuthering Heights",
    "image_url": "",
    "record_type": "library_book",
    "source_label": "Grace Balloch Memorial Library"
  },
  {
    "url": "https://spearfish.blackhills.bywatersolutions.com/cgi-bin/koha/opac-detail.pl?biblionumber=516249",
    "title": "The chosen and the damned",
    "image_url": "https://images-na.ssl-images-amazon.com/images/P/1635578388.01.LZZZZZZZ.jpg",
    "record_type": "library_book",
    "source_label": "Grace Balloch Memorial Library"
  },
  {
    "url": "https://spearfish.blackhills.bywatersolutions.com/cgi-bin/koha/opac-detail.pl?biblionumber=518490",
    "title": "Our perfect storm",
    "image_url": "https://images-na.ssl-images-amazon.com/images/P/059395324X.01.LZZZZZZZ.jpg",
    "record_type": "library_book",
    "source_label": "Grace Balloch Memorial Library"
  },
  {
    "url": "https://spearfish.blackhills.bywatersolutions.com/cgi-bin/koha/opac-detail.pl?biblionumber=521646",
    "title": "My first library",
    "image_url": "https://images-na.ssl-images-amazon.com/images/P/9387779262.01.LZZZZZZZ.jpg",
    "record_type": "library_book",
    "source_label": "Grace Balloch Memorial Library"
  },
  {
    "url": "https://spearfish.blackhills.bywatersolutions.com/cgi-bin/koha/opac-detail.pl?biblionumber=519882",
    "title": "Those who are about to die",
    "image_url": "https://images-na.ssl-images-amazon.com/images/P/0593801768.01.LZZZZZZZ.jpg",
    "record_type": "library_book",
    "source_label": "Grace Balloch Memorial Library"
  },
  {
    "url": "https://spearfish.blackhills.bywatersolutions.com/cgi-bin/koha/opac-detail.pl?biblionumber=518750",
    "title": "The brothers McKay",
    "image_url": "https://images-na.ssl-images-amazon.com/images/P/0593830733.01.LZZZZZZZ.jpg",
    "record_type": "library_book",
    "source_label": "Grace Balloch Memorial Library"
  },
  {
    "url": "https://spearfish.blackhills.bywatersolutions.com/cgi-bin/koha/opac-detail.pl?biblionumber=148084",
    "title": "The lion, the witch, and the wardrobe",
    "image_url": "https://images-na.ssl-images-amazon.com/images/P/0060234814.01.LZZZZZZZ.jpg",
    "record_type": "library_book",
    "source_label": "Grace Balloch Memorial Library"
  },
  {
    "url": "https://spearfish.blackhills.bywatersolutions.com/cgi-bin/koha/opac-detail.pl?biblionumber=518423",
    "title": "A sociopath's guide to a successful marriage",
    "image_url": "https://images-na.ssl-images-amazon.com/images/P/1668096900.01.LZZZZZZZ.jpg",
    "record_type": "library_book",
    "source_label": "Grace Balloch Memorial Library"
  },
  {
    "url": "https://spearfish.blackhills.bywatersolutions.com/cgi-bin/koha/opac-detail.pl?biblionumber=518288",
    "title": "My grandfather, the master detective",
    "image_url": "",
    "record_type": "library_book",
    "source_label": "Grace Balloch Memorial Library"
  },
  {
    "url": "https://spearfish.blackhills.bywatersolutions.com/cgi-bin/koha/opac-detail.pl?biblionumber=517820",
    "title": "Unspeakable things",
    "image_url": "https://images-na.ssl-images-amazon.com/images/P/1984880187.01.LZZZZZZZ.jpg",
    "record_type": "library_book",
    "source_label": "Grace Balloch Memorial Library"
  },
  {
    "url": "https://spearfish.blackhills.bywatersolutions.com/cgi-bin/koha/opac-detail.pl?biblionumber=4395",
    "title": "If you give a moose a muffin",
    "image_url": "https://images-na.ssl-images-amazon.com/images/P/0060244062.01.LZZZZZZZ.jpg",
    "record_type": "library_book",
    "source_label": "Grace Balloch Memorial Library"
  },
  {
    "url": "https://spearfish.blackhills.bywatersolutions.com/cgi-bin/koha/opac-detail.pl?biblionumber=48357",
    "title": "The good husband of Zebra Drive",
    "image_url": "https://images-na.ssl-images-amazon.com/images/P/0375422730.01.LZZZZZZZ.jpg",
    "record_type": "library_book",
    "source_label": "Grace Balloch Memorial Library"
  },
  {
    "url": "https://spearfish.blackhills.bywatersolutions.com/cgi-bin/koha/opac-detail.pl?biblionumber=128402",
    "title": "Santorini",
    "image_url": "https://images-na.ssl-images-amazon.com/images/P/0385231539.01.LZZZZZZZ.jpg",
    "record_type": "library_book",
    "source_label": "Grace Balloch Memorial Library"
  },
  {
    "url": "https://spearfish.blackhills.bywatersolutions.com/cgi-bin/koha/opac-detail.pl?biblionumber=223424",
    "title": "Pup and hound at sea",
    "image_url": "https://images-na.ssl-images-amazon.com/images/P/1553378040.01.LZZZZZZZ.jpg",
    "record_type": "library_book",
    "source_label": "Grace Balloch Memorial Library"
  },
  {
    "url": "https://spearfish.blackhills.bywatersolutions.com/cgi-bin/koha/opac-detail.pl?biblionumber=22689",
    "title": "When my name was Keoko",
    "image_url": "https://images-na.ssl-images-amazon.com/images/P/0618133356.01.LZZZZZZZ.jpg",
    "record_type": "library_book",
    "source_label": "Grace Balloch Memorial Library"
  },
  {
    "url": "https://spearfish.blackhills.bywatersolutions.com/cgi-bin/koha/opac-detail.pl?biblionumber=380877",
    "title": "Dreams for our daughters",
    "image_url": "https://images-na.ssl-images-amazon.com/images/P/080285558X.01.LZZZZZZZ.jpg",
    "record_type": "library_book",
    "source_label": "Grace Balloch Memorial Library"
  },
  {
    "url": "https://spearfish.blackhills.bywatersolutions.com/cgi-bin/koha/opac-detail.pl?biblionumber=303761",
    "title": "A game of thrones",
    "image_url": "https://images-na.ssl-images-amazon.com/images/P/0553103547.01.LZZZZZZZ.jpg",
    "record_type": "library_book",
    "source_label": "Grace Balloch Memorial Library"
  },
  {
    "url": "https://spearfish.blackhills.bywatersolutions.com/cgi-bin/koha/opac-detail.pl?biblionumber=180091",
    "title": "The new kid",
    "image_url": "https://images-na.ssl-images-amazon.com/images/P/0761320393.01.LZZZZZZZ.jpg",
    "record_type": "library_book",
    "source_label": "Grace Balloch Memorial Library"
  },
  {
    "url": "https://spearfish.blackhills.bywatersolutions.com/cgi-bin/koha/opac-detail.pl?biblionumber=98036",
    "title": "Stranded",
    "image_url": "https://images-na.ssl-images-amazon.com/images/P/0385535546.01.LZZZZZZZ.jpg",
    "record_type": "library_book",
    "source_label": "Grace Balloch Memorial Library"
  },
  {
    "url": "https://spearfish.blackhills.bywatersolutions.com/cgi-bin/koha/opac-detail.pl?biblionumber=311765",
    "title": "Dog Man and Cat Kid",
    "image_url": "https://images-na.ssl-images-amazon.com/images/P/1338741063.01.LZZZZZZZ.jpg",
    "record_type": "library_book",
    "source_label": "Grace Balloch Memorial Library"
  },
  {
    "url": "https://spearfish.blackhills.bywatersolutions.com/cgi-bin/koha/opac-detail.pl?biblionumber=357463",
    "title": "Princess Island",
    "image_url": "https://images-na.ssl-images-amazon.com/images/P/1937133508.01.LZZZZZZZ.jpg",
    "record_type": "library_book",
    "source_label": "Grace Balloch Memorial Library"
  },
  {
    "url": "https://spearfish.blackhills.bywatersolutions.com/cgi-bin/koha/opac-detail.pl?biblionumber=227189",
    "title": "Spider on the Floor",
    "image_url": "https://images-na.ssl-images-amazon.com/images/P/0517593815.01.LZZZZZZZ.jpg",
    "record_type": "library_book",
    "source_label": "Grace Balloch Memorial Library"
  },
  {
    "url": "https://spearfish.blackhills.bywatersolutions.com/cgi-bin/koha/opac-detail.pl?biblionumber=313191",
    "title": "Tiny Goes Camping",
    "image_url": "https://images-na.ssl-images-amazon.com/images/P/0140567410.01.LZZZZZZZ.jpg",
    "record_type": "library_book",
    "source_label": "Grace Balloch Memorial Library"
  },
  {
    "url": "https://spearfish.blackhills.bywatersolutions.com/cgi-bin/koha/opac-detail.pl?biblionumber=65375",
    "title": "Rebecca to the Rescue",
    "image_url": "https://images-na.ssl-images-amazon.com/images/P/1593695284.01.LZZZZZZZ.jpg",
    "record_type": "library_book",
    "source_label": "Grace Balloch Memorial Library"
  },
  {
    "url": "https://spearfish.blackhills.bywatersolutions.com/cgi-bin/koha/opac-detail.pl?biblionumber=91135",
    "title": "Victims",
    "image_url": "https://images-na.ssl-images-amazon.com/images/P/0345505719.01.LZZZZZZZ.jpg",
    "record_type": "library_book",
    "source_label": "Grace Balloch Memorial Library"
  },
  {
    "url": "https://spearfish.blackhills.bywatersolutions.com/cgi-bin/koha/opac-detail.pl?biblionumber=516766",
    "title": "Seeing stars!",
    "image_url": "https://images-na.ssl-images-amazon.com/images/P/141977624X.01.LZZZZZZZ.jpg",
    "record_type": "library_book",
    "source_label": "Grace Balloch Memorial Library"
  },
  {
    "url": "https://spearfish.blackhills.bywatersolutions.com/cgi-bin/koha/opac-detail.pl?biblionumber=519445",
    "title": "The faith of beasts",
    "image_url": "https://images-na.ssl-images-amazon.com/images/P/0316525677.01.LZZZZZZZ.jpg",
    "record_type": "library_book",
    "source_label": "Grace Balloch Memorial Library"
  },
  {
    "url": "https://spearfish.blackhills.bywatersolutions.com/cgi-bin/koha/opac-detail.pl?biblionumber=522452",
    "title": "Who hid the stars?",
    "image_url": "https://images-na.ssl-images-amazon.com/images/P/0802856519.01.LZZZZZZZ.jpg",
    "record_type": "library_book",
    "source_label": "Grace Balloch Memorial Library"
  },
  {
    "url": "https://spearfish.blackhills.bywatersolutions.com/cgi-bin/koha/opac-detail.pl?biblionumber=521069",
    "title": "Hope rises",
    "image_url": "https://images-na.ssl-images-amazon.com/images/P/153877920X.01.LZZZZZZZ.jpg",
    "record_type": "library_book",
    "source_label": "Grace Balloch Memorial Library"
  },
  {
    "url": "https://spearfish.blackhills.bywatersolutions.com/cgi-bin/koha/opac-detail.pl?biblionumber=522530",
    "title": "Nell O'Dell hates quests",
    "image_url": "https://images-na.ssl-images-amazon.com/images/P/1536243310.01.LZZZZZZZ.jpg",
    "record_type": "library_book",
    "source_label": "Grace Balloch Memorial Library"
  },
  {
    "url": "https://spearfish.blackhills.bywatersolutions.com/cgi-bin/koha/opac-detail.pl?biblionumber=522505",
    "title": "Laurentian divide",
    "image_url": "https://images-na.ssl-images-amazon.com/images/P/1517902495.01.LZZZZZZZ.jpg",
    "record_type": "library_book",
    "source_label": "Grace Balloch Memorial Library"
  },
  {
    "url": "https://spearfish.blackhills.bywatersolutions.com/cgi-bin/koha/opac-detail.pl?biblionumber=519183",
    "title": "The Aztecs",
    "image_url": "",
    "record_type": "library_book",
    "source_label": "Grace Balloch Memorial Library"
  },
  {
    "url": "https://spearfish.blackhills.bywatersolutions.com/cgi-bin/koha/opac-detail.pl?biblionumber=519626",
    "title": "Forgive-Me-Not",
    "image_url": "https://images-na.ssl-images-amazon.com/images/P/1250784174.01.LZZZZZZZ.jpg",
    "record_type": "library_book",
    "source_label": "Grace Balloch Memorial Library"
  },
  {
    "url": "https://spearfish.blackhills.bywatersolutions.com/cgi-bin/koha/opac-detail.pl?biblionumber=313962",
    "title": "Wicca",
    "image_url": "https://images-na.ssl-images-amazon.com/images/P/0875421180.01.LZZZZZZZ.jpg",
    "record_type": "library_book",
    "source_label": "Grace Balloch Memorial Library"
  },
  {
    "url": "https://spearfish.blackhills.bywatersolutions.com/cgi-bin/koha/opac-detail.pl?biblionumber=517894",
    "title": "The Brainstormerz: Money Talks (a Graphic Novel)",
    "image_url": "https://images-na.ssl-images-amazon.com/images/P/0316541087.01.LZZZZZZZ.jpg",
    "record_type": "library_book",
    "source_label": "Grace Balloch Memorial Library"
  },
  {
    "url": "https://spearfish.blackhills.bywatersolutions.com/cgi-bin/koha/opac-detail.pl?biblionumber=516727",
    "title": "Star stories",
    "image_url": "https://images-na.ssl-images-amazon.com/images/P/1536227587.01.LZZZZZZZ.jpg",
    "record_type": "library_book",
    "source_label": "Grace Balloch Memorial Library"
  },
  {
    "url": "https://spearfish.blackhills.bywatersolutions.com/cgi-bin/koha/opac-detail.pl?biblionumber=367063",
    "title": "Bonhoeffer",
    "image_url": "https://images-na.ssl-images-amazon.com/images/P/1595551387.01.LZZZZZZZ.jpg",
    "record_type": "library_book",
    "source_label": "Grace Balloch Memorial Library"
  },
  {
    "url": "https://spearfish.blackhills.bywatersolutions.com/cgi-bin/koha/opac-detail.pl?biblionumber=522567",
    "title": "Unbreakable",
    "image_url": "https://images-na.ssl-images-amazon.com/images/P/1419772899.01.LZZZZZZZ.jpg",
    "record_type": "library_book",
    "source_label": "Grace Balloch Memorial Library"
  },
  {
    "url": "https://spearfish.blackhills.bywatersolutions.com/cgi-bin/koha/opac-detail.pl?biblionumber=521055",
    "title": "The manual to middle school",
    "image_url": "https://images-na.ssl-images-amazon.com/images/P/0800728475.01.LZZZZZZZ.jpg",
    "record_type": "library_book",
    "source_label": "Grace Balloch Memorial Library"
  },
  {
    "url": "https://spearfish.blackhills.bywatersolutions.com/cgi-bin/koha/opac-detail.pl?biblionumber=522466",
    "title": "Clock hands",
    "image_url": "https://images-na.ssl-images-amazon.com/images/P/0063027135.01.LZZZZZZZ.jpg",
    "record_type": "library_book",
    "source_label": "Grace Balloch Memorial Library"
  }
]